deepnox/__init__.py
deepnox/aiobox/__init__.py
deepnox/aiobox/base.py
deepnox/aiorest/__init__.py
deepnox/aiorest/api.py
deepnox/aiorest/client.py
deepnox/aiorest/requester.py
deepnox/aiorest/resources.py
deepnox/auth/__init__.py
deepnox/auth/credentials.py
deepnox/clients/__init__.py
deepnox/clients/aiohttpclient.py
deepnox/clients/http_client.py
deepnox/core/__init__.py
deepnox/core/base.py
deepnox/core/enumerations.py
deepnox/files/__init__.py
deepnox/files/base.py
deepnox/helpers/__init__.py
deepnox/helpers/testing_helpers.py
deepnox/loggers/__init__.py
deepnox/loggers/defaults.py
deepnox/loggers/formatters/__init__.py
deepnox/loggers/formatters/base_formatter.py
deepnox/loggers/formatters/json_formatter.py
deepnox/loggers/formatters/locust_formatters.py
deepnox/loggers/formatters/logstash_formatter.py
deepnox/loggers/formatters/result_formatter.py
deepnox/loggers/formatters/yaml_formatter.py
deepnox/models/__init__.py
deepnox/network/__init__.py
deepnox/network/auth.py
deepnox/network/content_types.py
deepnox/network/http.py
deepnox/network/schemes.py
deepnox/network/uri.py
deepnox/network/urls.py
deepnox/patterns/__init__.py
deepnox/patterns/services_base.py
deepnox/repositories/__init__.py
deepnox/repositories/repositories_base.py
deepnox/serializers/__init__.py
deepnox/serializers/base_serializer.py
deepnox/serializers/json_serializer.py
deepnox/serializers/pickle_serializer.py
deepnox/serializers/yaml_serializer.py
deepnox/settings/__init__.py
deepnox/settings/base.py
deepnox/tests/__init__.py
deepnox/tests/run_tests.py
deepnox/tests/helpers/__init__.py
deepnox/tests/helpers/filesystem.py
deepnox/tests/helpers/helpers_pkg_test.py
deepnox/tests/helpers/mock.py
deepnox/tests/helpers/testing_helpers_test.py
deepnox/third/__init__.py
deepnox/third/aiohttp_.py
deepnox/third/jinja2.py
deepnox/utils/__init__.py
deepnox/utils/audit.py
deepnox/utils/chronometer.py
deepnox/utils/datetime_utils.py
deepnox/utils/exceptions.py
deepnox/utils/maps.py
wipbox-0.0.14.2.dist-info/LICENSE
wipbox-0.0.14.2.dist-info/METADATA
wipbox-0.0.14.2.dist-info/WHEEL
wipbox-0.0.14.2.dist-info/top_level.txt
wipbox-0.0.14.2.dist-info/RECORD
