Metadata-Version: 2.1
Name: wipbox
Version: 0.0.14.2
Summary: A set of modern Python libraries under development to simplify the execution of reusable routines by different projects.
Home-page: https://github.com/deepnox-io/pythpn-wipbox
Author: The Deepnox team
Author-email: contact@deepnox.io
License: Copyrighted 2021-2022, Deepnox SAS
Download-URL: https://github.com/deepnox-io/pythpn-wipbox/0.0.14.2.tar.gz
Keywords: deepnox,wipbox,utilities,tools,various,work in progress,draft
Platform: UNKNOWN
Classifier: Development Status :: 2 - Pre-Alpha
Classifier: Topic :: Software Development :: Libraries
Classifier: License :: OSI Approved :: MIT License
Classifier: Programming Language :: Python :: 3.9
License-File: LICENSE
Requires-Dist: arrow (~=1.2.1)
Requires-Dist: aiofiles (~=0.7.0)
Requires-Dist: aiohttp (~=3.8.0)
Requires-Dist: Jinja2 (~=3.0.3)
Requires-Dist: jsonpath-ng (~=1.5.3)
Requires-Dist: pandas (~=1.3.4)
Requires-Dist: pydantic (~=1.9.0)
Requires-Dist: pyyaml (~=6.0)
Requires-Dist: pyfakefs (~=4.5.3)
Requires-Dist: requests (~=2.26.0)
Requires-Dist: shortuuid (~=1.0.8)
